lockana/__init__.py
lockana/admin.py
lockana/auth.py
lockana/client.py
lockana/logs.py
lockana/secrets.py
test/__init__.py
test/manual_tests.py
test/unit_tests.py
python_lockana-0.1.0.dist-info/LICENSE
python_lockana-0.1.0.dist-info/METADATA
python_lockana-0.1.0.dist-info/WHEEL
python_lockana-0.1.0.dist-info/top_level.txt
python_lockana-0.1.0.dist-info/RECORD
