Metadata-Version: 2.1
Name: python-lockana
Version: 0.1.0
Summary: Python wrapper for the Lockana API
Home-page: https://github.com/NullPointerGang/Lockana-Python
Author: FlacSy
Author-email: flacsy.x@gmail.com
Requires-Python: >=3.10.0
License-File: LICENSE
Requires-Dist: requests
